setup.cfg
setup.py
gitkeep/__init__.py
gitkeep/main.py
gitkeep.egg-info/PKG-INFO
gitkeep.egg-info/SOURCES.txt
gitkeep.egg-info/dependency_links.txt
gitkeep.egg-info/entry_points.txt
gitkeep.egg-info/top_level.txt