Metadata-Version: 1.0
Name: gitkeep
Version: 0.0.3
Summary: Add .gitkeep file to empty folders.
Home-page: https://github.com/Frederick-S/gitkeep
Author: UNKNOWN
Author-email: UNKNOWN
License: UNKNOWN
Platform: UNKNOWN
